{
  "root": "/media/metamobility3/Samsung_T51/Processed/Jinwoo_Final",
  "n_subject_h5_files": 70,
  "n_h5_files_total": 70,
  "bad_subject_filename": [],
  "n_unique_conditions": 216,
  "n_unique_trial_leaf_names": 389,
  "n_unique_subject_condition_trial_triples": 21252,
  "unique_conditions_sorted": [
    "LevelGround",
    "Ramp",
    "Stair",
    "Static",
    "Treadmill",
    "ball_toss",
    "curb_down",
    "curb_up",
    "cutting",
    "dynamic_walk",
    "incline_ramp_1_l",
    "incline_ramp_1_r",
    "incline_ramp_2_l",
    "incline_ramp_2_r",
    "incline_ramp_3_l",
    "incline_ramp_3_r",
    "incline_ramp_4_l",
    "incline_ramp_4_r",
    "incline_ramp_5_l",
    "incline_ramp_5_r",
    "incline_ramp_6_l",
    "incline_ramp_6_r",
    "incline_treadmill_bundle1",
    "incline_treadmill_bundle2",
    "incline_treadmill_down10deg",
    "incline_treadmill_down10deg_0mps",
    "incline_treadmill_down10deg_0p4mps",
    "incline_treadmill_down10deg_0p6mps",
    "incline_treadmill_down10deg_0p8mps",
    "incline_treadmill_down10deg_1p0mps",
    "incline_treadmill_down10deg_transient_15s",
    "incline_treadmill_down10deg_transient_30s",
    "incline_treadmill_down5deg",
    "incline_treadmill_down5deg_0mps",
    "incline_treadmill_down5deg_0p4mps",
    "incline_treadmill_down5deg_0p6mps",
    "incline_treadmill_down5deg_0p8mps",
    "incline_treadmill_down5deg_1p0mps",
    "incline_treadmill_down5deg_transient_15s",
    "incline_treadmill_down5deg_transient_30s",
    "incline_treadmill_up10deg",
    "incline_treadmill_up10deg_0mps",
    "incline_treadmill_up10deg_0p4mps",
    "incline_treadmill_up10deg_0p6mps",
    "incline_treadmill_up10deg_0p8mps",
    "incline_treadmill_up10deg_1p0mps",
    "incline_treadmill_up10deg_transient_15s",
    "incline_treadmill_up10deg_transient_30s",
    "incline_treadmill_up5deg",
    "incline_treadmill_up5deg_0mps",
    "incline_treadmill_up5deg_0p4mps",
    "incline_treadmill_up5deg_0p6mps",
    "incline_treadmill_up5deg_0p8mps",
    "incline_treadmill_up5deg_1p0mps",
    "incline_treadmill_up5deg_transient_15s",
    "incline_treadmill_up5deg_transient_30s",
    "incline_walk",
    "incline_walk_3",
    "incline_walk_4",
    "jump",
    "jump_180_turn",
    "jump_90_turn_1",
    "jump_90_turn_2",
    "jump_bundle1",
    "jump_bundle2",
    "jump_bundle3",
    "jump_forward_back",
    "jump_forward_back_run2",
    "jump_hop",
    "jump_hop_run2",
    "jump_lateral",
    "jump_vertical",
    "jump_vertical_run2",
    "levelground_ccw_fast",
    "levelground_ccw_normal",
    "levelground_ccw_slow",
    "levelground_curb_down",
    "levelground_curb_down_bundle1",
    "levelground_curb_up",
    "levelground_curb_up_bundle1",
    "levelground_cut_left_fast",
    "levelground_cut_left_slow",
    "levelground_cut_right_fast",
    "levelground_cut_right_slow",
    "levelground_cutting_bundle1",
    "levelground_cw_fast",
    "levelground_cw_normal",
    "levelground_cw_slow",
    "levelground_heel_walk_0p4mps",
    "levelground_meander",
    "levelground_meander_bundle1",
    "levelground_start_stop",
    "levelground_start_stop_bundle1",
    "levelground_toe_walk_0p4mps",
    "levelground_turn_step_bundle1",
    "levelground_turn_step_left",
    "levelground_turn_step_right",
    "lift_weight",
    "lunges",
    "meander",
    "normal_walk",
    "normal_walk_2",
    "normal_walk_3",
    "obstacle_walk",
    "perturbation_push_bundle1",
    "perturbation_push_pull",
    "poses",
    "push",
    "side_shuffle",
    "sit_to_stand",
    "sport_ball_toss_bundle1",
    "sport_ball_toss_center",
    "sport_ball_toss_left",
    "sport_ball_toss_left_seg2",
    "sport_ball_toss_right",
    "sport_side_shuffle",
    "sport_side_shuffle_bundle1",
    "sport_tire_run",
    "sport_tire_run_bundle1",
    "sport_tug_of_war",
    "sport_tug_of_war_bundle1",
    "sport_twister",
    "sport_twister_bundle1",
    "squats",
    "stair_10_down",
    "stair_11_up",
    "stair_12_down",
    "stair_1_l",
    "stair_1_r",
    "stair_1_up",
    "stair_2_down",
    "stair_2_l",
    "stair_2_r",
    "stair_3_l",
    "stair_3_r",
    "stair_3_up",
    "stair_4_down",
    "stair_4_l",
    "stair_4_r",
    "stair_5_up",
    "stair_6_down",
    "stair_7_up",
    "stair_8_down",
    "stair_9_up",
    "stair_bundle2",
    "stair_bundle3",
    "stairs_1",
    "stairs_1_1",
    "stairs_2_1",
    "start_stop",
    "static_poses_bundle1",
    "static_poses_varied",
    "static_standing",
    "step_ups",
    "strength_lift_0lb_left_center",
    "strength_lift_0lb_left_lateral",
    "strength_lift_0lb_right_center",
    "strength_lift_0lb_right_lateral",
    "strength_lift_25lb_left_center",
    "strength_lift_25lb_left_lateral",
    "strength_lift_25lb_right_center",
    "strength_lift_25lb_right_lateral",
    "strength_lift_bundle1",
    "strength_lift_bundle2",
    "strength_lunge_bundle1",
    "strength_lunge_bundle2",
    "strength_lunge_fwd_back",
    "strength_lunge_side_left",
    "strength_lunge_side_right",
    "strength_sit_to_stand_bundle1",
    "strength_sit_to_stand_bundle2",
    "strength_sit_to_stand_short_arm",
    "strength_sit_to_stand_short_arm_run2",
    "strength_sit_to_stand_short_noarm",
    "strength_sit_to_stand_tall_noarm",
    "strength_squat_bundle1",
    "strength_squat_loaded_25lb",
    "strength_squat_unloaded",
    "strength_step_up_bundle1",
    "strength_step_up_left",
    "strength_step_up_right",
    "tire_run",
    "treadmill_0p0mps",
    "treadmill_0p2mps",
    "treadmill_0p4mps",
    "treadmill_0p6mps",
    "treadmill_0p8mps",
    "treadmill_1p0mps",
    "treadmill_1p2mps",
    "treadmill_1p4mps",
    "treadmill_1p8mps",
    "treadmill_2p0mps",
    "treadmill_2p5mps",
    "treadmill_backward_0p6mps",
    "treadmill_backward_0p8mps",
    "treadmill_backward_1p0mps",
    "treadmill_backward_bundle1",
    "treadmill_calisthenics_butt_kicks",
    "treadmill_calisthenics_high_knees",
    "treadmill_dynamic_walk_bundle1",
    "treadmill_normal_walk_bundle1",
    "treadmill_obstacle_1p0mps",
    "treadmill_obstacle_bundle1",
    "treadmill_shuffle_0p4mps",
    "treadmill_skip_1p2mps",
    "treadmill_transient_15s",
    "treadmill_transient_30s",
    "treadmill_unspecified_speed",
    "treadmill_weighted_25lb",
    "treadmill_weighted_bundle1",
    "tug_of_war",
    "turn_and_step",
    "twister",
    "walk_backward",
    "walk_backward_2",
    "weighted_walk"
  ],
  "unique_trial_leaves_sorted": [
    "trial_01",
    "trial_02",
    "trial_03",
    "trial_04",
    "trial_05",
    "trial_06",
    "trial_07",
    "trial_08",
    "trial_09",
    "trial_10",
    "trial_11",
    "trial_12",
    "trial_13",
    "trial_14",
    "trial_15",
    "trial_16",
    "trial_17",
    "trial_18",
    "trial_19",
    "trial_20",
    "trial_21",
    "trial_22",
    "trial_23",
    "trial_24",
    "trial_25",
    "trial_26",
    "trial_27",
    "trial_28",
    "trial_29",
    "trial_30",
    "trial_31",
    "trial_32",
    "trial_33",
    "trial_34",
    "trial_35",
    "trial_36",
    "trial_37",
    "trial_38",
    "trial_39",
    "trial_40",
    "trial_41",
    "trial_42",
    "trial_43",
    "trial_44",
    "trial_45",
    "trial_46",
    "trial_47",
    "trial_48",
    "trial_49",
    "trial_50",
    "trial_51",
    "trial_52",
    "trial_53",
    "trial_54",
    "trial_55",
    "trial_56",
    "trial_57",
    "trial_58",
    "trial_59",
    "trial_60",
    "trial_61",
    "trial_62",
    "trial_63",
    "trial_64",
    "trial_65",
    "trial_66",
    "trial_67",
    "trial_68",
    "trial_69",
    "trial_70",
    "trial_71",
    "trial_72",
    "trial_73",
    "trial_74",
    "trial_75",
    "trial_76",
    "trial_77",
    "trial_78",
    "trial_79",
    "trial_80",
    "trial_81",
    "trial_82",
    "trial_83",
    "trial_84",
    "trial_85",
    "trial_86",
    "trial_87",
    "trial_88",
    "trial_89",
    "trial_90",
    "trial_91",
    "trial_92",
    "trial_93",
    "trial_94",
    "trial_95",
    "trial_96",
    "trial_97",
    "trial_98",
    "trial_99",
    "trial_100",
    "trial_101",
    "trial_102",
    "trial_103",
    "trial_104",
    "trial_105",
    "trial_106",
    "trial_107",
    "trial_108",
    "trial_109",
    "trial_110",
    "trial_111",
    "trial_112",
    "trial_113",
    "trial_114",
    "trial_115",
    "trial_116",
    "trial_117",
    "trial_118",
    "trial_119",
    "trial_120",
    "trial_121",
    "trial_122",
    "trial_123",
    "trial_124",
    "trial_125",
    "trial_126",
    "trial_127",
    "trial_128",
    "trial_129",
    "trial_130",
    "trial_131",
    "trial_132",
    "trial_133",
    "trial_134",
    "trial_135",
    "trial_136",
    "trial_137",
    "trial_138",
    "trial_139",
    "trial_140",
    "trial_141",
    "trial_142",
    "trial_143",
    "trial_144",
    "trial_145",
    "trial_146",
    "trial_147",
    "trial_148",
    "trial_149",
    "trial_150",
    "trial_151",
    "trial_152",
    "trial_153",
    "trial_154",
    "trial_155",
    "trial_156",
    "trial_157",
    "trial_158",
    "trial_159",
    "trial_160",
    "trial_161",
    "trial_162",
    "trial_163",
    "trial_164",
    "trial_165",
    "trial_166",
    "trial_167",
    "trial_168",
    "trial_169",
    "trial_170",
    "trial_171",
    "trial_172",
    "trial_173",
    "trial_174",
    "trial_175",
    "trial_176",
    "trial_177",
    "trial_178",
    "trial_179",
    "trial_180",
    "trial_181",
    "trial_182",
    "trial_183",
    "trial_184",
    "trial_185",
    "trial_186",
    "trial_187",
    "trial_188",
    "trial_189",
    "trial_190",
    "trial_191",
    "trial_192",
    "trial_193",
    "trial_194",
    "trial_195",
    "trial_196",
    "trial_197",
    "trial_198",
    "trial_199",
    "trial_200",
    "trial_201",
    "trial_202",
    "trial_203",
    "trial_204",
    "trial_205",
    "trial_206",
    "trial_207",
    "trial_208",
    "trial_209",
    "trial_210",
    "trial_211",
    "trial_212",
    "trial_213",
    "trial_214",
    "trial_215",
    "trial_216",
    "trial_217",
    "trial_218",
    "trial_219",
    "trial_220",
    "trial_221",
    "trial_222",
    "trial_223",
    "trial_224",
    "trial_225",
    "trial_226",
    "trial_227",
    "trial_228",
    "trial_229",
    "trial_230",
    "trial_231",
    "trial_232",
    "trial_233",
    "trial_234",
    "trial_235",
    "trial_236",
    "trial_237",
    "trial_238",
    "trial_239",
    "trial_240",
    "trial_241",
    "trial_242",
    "trial_243",
    "trial_244",
    "trial_245",
    "trial_246",
    "trial_247",
    "trial_248",
    "trial_249",
    "trial_250",
    "trial_251",
    "trial_252",
    "trial_253",
    "trial_254",
    "trial_255",
    "trial_256",
    "trial_257",
    "trial_258",
    "trial_259",
    "trial_260",
    "trial_261",
    "trial_262",
    "trial_263",
    "trial_264",
    "trial_265",
    "trial_266",
    "trial_267",
    "trial_268",
    "trial_269",
    "trial_270",
    "trial_271",
    "trial_272",
    "trial_273",
    "trial_274",
    "trial_275",
    "trial_276",
    "trial_277",
    "trial_278",
    "trial_279",
    "trial_280",
    "trial_281",
    "trial_282",
    "trial_283",
    "trial_284",
    "trial_285",
    "trial_286",
    "trial_287",
    "trial_288",
    "trial_289",
    "trial_290",
    "trial_291",
    "trial_292",
    "trial_293",
    "trial_294",
    "trial_295",
    "trial_296",
    "trial_297",
    "trial_298",
    "trial_299",
    "trial_300",
    "trial_301",
    "trial_302",
    "trial_303",
    "trial_304",
    "trial_305",
    "trial_306",
    "trial_307",
    "trial_308",
    "trial_309",
    "trial_310",
    "trial_311",
    "trial_312",
    "trial_313",
    "trial_314",
    "trial_315",
    "trial_316",
    "trial_317",
    "trial_318",
    "trial_319",
    "trial_320",
    "trial_321",
    "trial_322",
    "trial_323",
    "trial_324",
    "trial_325",
    "trial_326",
    "trial_327",
    "trial_328",
    "trial_329",
    "trial_330",
    "trial_331",
    "trial_332",
    "trial_333",
    "trial_334",
    "trial_335",
    "trial_336",
    "trial_337",
    "trial_338",
    "trial_339",
    "trial_340",
    "trial_341",
    "trial_342",
    "trial_343",
    "trial_344",
    "trial_345",
    "trial_346",
    "trial_347",
    "trial_348",
    "trial_349",
    "trial_350",
    "trial_351",
    "trial_352",
    "trial_353",
    "trial_354",
    "trial_355",
    "trial_356",
    "trial_357",
    "trial_358",
    "trial_359",
    "trial_360",
    "trial_361",
    "trial_362",
    "trial_363",
    "trial_364",
    "trial_365",
    "trial_366",
    "trial_367",
    "trial_368",
    "trial_369",
    "trial_370",
    "trial_371",
    "trial_372",
    "trial_373",
    "trial_374",
    "trial_375",
    "trial_376",
    "trial_377",
    "trial_378",
    "trial_379",
    "trial_380",
    "trial_381",
    "trial_382",
    "trial_383",
    "trial_384",
    "trial_385",
    "trial_386",
    "trial_387",
    "trial_388",
    "trial_389"
  ],
  "n_issues": 0,
  "issues": []
}